noisets/__init__.py
noisets/detection_learning.py
noisets/generator.py
noisets/noise_learning.py
noisets/noisettes.py
noisets-0.0.1.dist-info/LICENSE
noisets-0.0.1.dist-info/METADATA
noisets-0.0.1.dist-info/WHEEL
noisets-0.0.1.dist-info/entry_points.txt
noisets-0.0.1.dist-info/top_level.txt
noisets-0.0.1.dist-info/RECORD
