Metadata-Version: 2.1
Name: noisets
Version: 0.0.1
Summary: A package assessing experimental sampling Noise and follows TCR dynamics with time
Home-page:  
Author: Meriem Bensouda Koraichi 
Author-email: meriem.bensoudakoraichi@gmail.com
License: UNKNOWN
Keywords: package numbers calculations
Platform: UNKNOWN
Classifier: Programming Language :: Python :: 3
Classifier: Operating System :: OS Independent
License-File: LICENSE
